card_magic_mcp/__init__.py
card_magic_mcp/__main__.py
card_magic_mcp/magic.py
card_magic_mcp/server.py
card_magic_mcp-1.0.9.dist-info/METADATA
card_magic_mcp-1.0.9.dist-info/WHEEL
card_magic_mcp-1.0.9.dist-info/entry_points.txt
card_magic_mcp-1.0.9.dist-info/licenses/LICENSE
card_magic_mcp-1.0.9.dist-info/RECORD
