Metadata-Version: 2.4
Name: card_magic_mcp
Version: 1.0.9
Summary: A Model Context Protocol (MCP) server that implements the Chico & Dico card magic trick.
Project-URL: repository, https://github.com/luochang212/card-magic-mcp
Project-URL: bug-tracker, https://github.com/luochang212/card-magic-mcp/issues
Project-URL: documentation, https://luochang212.github.io/posts/card_magic_mcp
Author: luochang
Author-email: luochang212@gmail.com
License: Apache-2.0
License-File: LICENSE
Keywords: magic,poker
Classifier: License :: OSI Approved :: Apache Software License
Classifier: Operating System :: MacOS
Classifier: Operating System :: Microsoft :: Windows
Classifier: Operating System :: Unix
Classifier: Programming Language :: Python
Classifier: Programming Language :: Python :: 3 :: Only
Classifier: Programming Language :: Python :: 3.10
Classifier: Programming Language :: Python :: 3.11
Classifier: Programming Language :: Python :: 3.12
Classifier: Topic :: Scientific/Engineering :: Mathematics
Requires-Python: >=3.10
Requires-Dist: fastmcp>=2.10.2
